Orbaplaw/__init__.py
Orbaplaw/main.py
Orbaplaw/Integrals/Pyscf.py
Orbaplaw/Integrals/__init__.py
Orbaplaw/Localization/Fock.py
Orbaplaw/Localization/FosterBoys.py
Orbaplaw/Localization/Localizer.py
Orbaplaw/Localization/Orbitalet.py
Orbaplaw/Localization/PipekMezey.py
Orbaplaw/Localization/PipekMezey_legacy.py
Orbaplaw/Localization/__init__.py
Orbaplaw/Localization/__init___legacy.py
Orbaplaw/Miscellany/FormatRange.py
Orbaplaw/Miscellany/ReadTXT.py
Orbaplaw/Miscellany/__init__.py
Orbaplaw/NaturalBondOrbitalMethods/NaturalAtomicOrbital.py
Orbaplaw/NaturalBondOrbitalMethods/NaturalBondOrbital.py
Orbaplaw/NaturalBondOrbitalMethods/PrincipalInteractingOrbital.py
Orbaplaw/NaturalBondOrbitalMethods/__init__.py
Orbaplaw/Optimization/DirectionSearch.py
Orbaplaw/Optimization/LineSearch.py
Orbaplaw/Optimization/UnitaryOptimizer.py
Orbaplaw/Optimization/__init__.py
Orbaplaw/OrbitalAlignment/FragmentAlignment.py
Orbaplaw/OrbitalAlignment/OrbitalAlignment.py
Orbaplaw/OrbitalAlignment/SpinAlignment.py
Orbaplaw/OrbitalAlignment/__init__.py
Orbaplaw/Population/Lowdin.py
Orbaplaw/Population/PopulationAnalyzer.py
Orbaplaw/Population/__init__.py
Orbaplaw/WaveFunction/Cube.py
Orbaplaw/WaveFunction/MultiWaveFunction.py
Orbaplaw/WaveFunction/QeWaveFunction.py
Orbaplaw/WaveFunction/__init__.py
orbaplaw-2.0.2.dist-info/licenses/LICENSE
orbaplaw-2.0.2.dist-info/METADATA
orbaplaw-2.0.2.dist-info/WHEEL
orbaplaw-2.0.2.dist-info/entry_points.txt
orbaplaw-2.0.2.dist-info/top_level.txt
orbaplaw-2.0.2.dist-info/RECORD
