Metadata-Version: 2.4
Name: Orbaplaw
Version: 2.0.2
Summary: Orbital alignment analysis for plane wave basis sets
Home-page: https://github.com/FreemanTheMaverick/Orbaplaw.git
Author: FreemanTheMaverick
Classifier: Programming Language :: Python :: 3
Requires-Python: >=3.10
License-File: LICENSE
Requires-Dist: numpy
Requires-Dist: scipy
Requires-Dist: pyscf
Requires-Dist: Maniverse>=1.0.0
Requires-Dist: libmwfn
Dynamic: author
Dynamic: classifier
Dynamic: description
Dynamic: description-content-type
Dynamic: home-page
Dynamic: license-file
Dynamic: requires-dist
Dynamic: requires-python
Dynamic: summary
